pulsing/__init__.py
pulsing/_core.abi3.so
pulsing/actor/__init__.py
pulsing/actor/helpers.py
pulsing/actor/remote.py
pulsing/actors/__init__.py
pulsing/actors/load_stream.py
pulsing/actors/router.py
pulsing/actors/scheduler.py
pulsing/actors/vllm/__init__.py
pulsing/actors/vllm/handlers.py
pulsing/actors/vllm/sampling.py
pulsing/actors/vllm/utils.py
pulsing/actors/vllm/worker.py
pulsing/actors/vllm_worker.py
pulsing/actors/worker.py
pulsing/admin.py
pulsing/agent/__init__.py
pulsing/agent/base.py
pulsing/agent/llm.py
pulsing/agent/runtime.py
pulsing/agent/utils.py
pulsing/autogen/__init__.py
pulsing/autogen/agent_wrapper.py
pulsing/autogen/runtime.py
pulsing/cli/__init__.py
pulsing/cli/__main__.py
pulsing/cli/actor_loader.py
pulsing/cli/actors.py
pulsing/cli/bench.py
pulsing/cli/inspect.py
pulsing/compat/__init__.py
pulsing/compat/ray.py
pulsing/exceptions.py
pulsing/langgraph/__init__.py
pulsing/langgraph/executor.py
pulsing/langgraph/wrapper.py
pulsing/queue/README.md
pulsing/queue/__init__.py
pulsing/queue/backend.py
pulsing/queue/manager.py
pulsing/queue/queue.py
pulsing/queue/storage.py
pulsing/queue/sync_queue.py
pulsing/topic/README.md
pulsing/topic/__init__.py
pulsing/topic/broker.py
pulsing/topic/topic.py
pulsing-0.1.0.dist-info/METADATA
pulsing-0.1.0.dist-info/WHEEL
pulsing-0.1.0.dist-info/entry_points.txt
pulsing-0.1.0.dist-info/licenses/LICENSE
pulsing-0.1.0.dist-info/RECORD
