Metadata-Version: 2.4
Name: pulsing
Version: 0.1.0
Classifier: Development Status :: 4 - Beta
Classifier: Intended Audience :: Developers
Classifier: Intended Audience :: Science/Research
Classifier: License :: OSI Approved :: Apache Software License
Classifier: Programming Language :: Python :: 3
Classifier: Programming Language :: Python :: 3.10
Classifier: Programming Language :: Python :: 3.11
Classifier: Programming Language :: Python :: 3.12
Classifier: Topic :: Software Development :: Libraries
Classifier: Topic :: Scientific/Engineering :: Artificial Intelligence
Classifier: Operating System :: POSIX :: Linux
Requires-Dist: pydantic>=2.10.6,<=2.11.7
Requires-Dist: uvloop>=0.21.0
Requires-Dist: aiohttp>=3.9.0
Requires-Dist: hyperparameter>=0.5.0
Requires-Dist: pytest>=8.0 ; extra == 'dev'
Requires-Dist: pytest-asyncio>=0.23 ; extra == 'dev'
Requires-Dist: ruff>=0.8 ; extra == 'dev'
Requires-Dist: maturin>=1.0 ; extra == 'dev'
Requires-Dist: pylance ; extra == 'dev'
Requires-Dist: pyarrow>=22.0.0 ; extra == 'dev'
Requires-Dist: pylance ; extra == 'storage'
Requires-Dist: pyarrow>=22.0.0 ; extra == 'storage'
Provides-Extra: dev
Provides-Extra: storage
License-File: LICENSE
Summary: Pulsing - Distributed Actor Framework
Keywords: actor,distributed,async,llm,inference
Author-email: Reiase <reiase@gmail.com>
License-Expression: Apache-2.0
Requires-Python: >=3.10
Project-URL: Changelog, https://github.com/reiase/pulsing/blob/main/CHANGELOG.md
Project-URL: Documentation, https://github.com/reiase/pulsing#readme
Project-URL: Homepage, https://github.com/reiase/pulsing
Project-URL: Issues, https://github.com/reiase/pulsing/issues
Project-URL: Repository, https://github.com/reiase/pulsing
